smml/__init__.py
smml/data_model_helper/__init__.py
smml/data_model_helper/_batch_file_manager.py
smml/data_model_helper/_container.py
smml/data_model_helper/_index.py
smml/data_model_helper/_io_helper.py
smml/data_model_helper/_numpy_model.py
smml/data_model_helper/_pandas_model.py
smml/data_model_helper/_polars_model.py
smml/data_model_helper/_raw_model.py
smml/dataset/__init__.py
smml/dataset/_columnar_dataset.py
smml/dataset/_dataset_helper.py
smml/dataset_helper.py
smml/misc.py
smml-1.0.2.dist-info/METADATA
smml-1.0.2.dist-info/WHEEL
smml-1.0.2.dist-info/RECORD
